{
    "data": [
        {
            "magnitude": "36.40054944640259",
            "Lat": "24.1792763",
            "Lng": "120.6493896"
        },
        {
            "magnitude": "38.28837943815329",
            "Lat": "24.1792763",
            "Lng": "120.6493895"
        },
        {
            "magnitude": "37.64306044943742",
            "Lat": "24.1792731",
            "Lng": "120.6493922"
        },
        {
            "magnitude": "37.013511046643494",
            "Lat": "24.1792746",
            "Lng": "120.6493923"
        },
        {
            "magnitude": "37.013511046643494",
            "Lat": "24.1792746",
            "Lng": "120.6493923"
        },
        {
            "magnitude": "38.65229618017538",
            "Lat": "24.1793194",
            "Lng": "120.6493686"
        },
        {
            "magnitude": "33.67491648096547",
            "Lat": "24.1792978",
            "Lng": "120.6493874"
        },
        {
            "magnitude": "53.225933528685054",
            "Lat": "24.1792981",
            "Lng": "120.649388"
        },
        {
            "magnitude": "53.59104402789705",
            "Lat": "24.1793283",
            "Lng": "120.6493732"
        },
        {
            "magnitude": "31.874754901018456",
            "Lat": "24.1793121",
            "Lng": "120.6493668"
        },
        {
            "magnitude": "32.526911934581186",
            "Lat": "24.179314",
            "Lng": "120.6493757"
        },
        {
            "magnitude": "32.526911934581186",
            "Lat": "24.179314",
            "Lng": "120.6493757"
        },
        {
            "magnitude": "41.24318125460256",
            "Lat": "24.1794339",
            "Lng": "120.6493156"
        },
        {
            "magnitude": "49.57822102496216",
            "Lat": "24.17944",
            "Lng": "120.6493035"
        },
        {
            "magnitude": "39.370039370059054",
            "Lat": "24.1794491",
            "Lng": "120.6492931"
        },
        {
            "magnitude": "31.464265445104548",
            "Lat": "24.1794446",
            "Lng": "120.6492848"
        },
        {
            "magnitude": "29.086079144497972",
            "Lat": "24.1794214",
            "Lng": "120.6492213"
        },
        {
            "magnitude": "33.52610922848042",
            "Lat": "24.1793668",
            "Lng": "120.6492016"
        },
        {
            "magnitude": "34.058772731852805",
            "Lat": "24.1794023",
            "Lng": "120.6491777"
        },
        {
            "magnitude": "60.55575942881073",
            "Lat": "24.179363",
            "Lng": "120.6491773"
        },
        {
            "magnitude": "41.400483088968905",
            "Lat": "24.1794039",
            "Lng": "120.64917"
        },
        {
            "magnitude": "30.56141357987225",
            "Lat": "24.1793322",
            "Lng": "120.6491712"
        },
        {
            "magnitude": "43.15089802078283",
            "Lat": "24.1793333",
            "Lng": "120.6491894"
        },
        {
            "magnitude": "51.67204273105525",
            "Lat": "24.1792913",
            "Lng": "120.648778"
        },
        {
            "magnitude": "56.444663166680336",
            "Lat": "24.1791281",
            "Lng": "120.6489118"
        },
        {
            "magnitude": "49.77951385861457",
            "Lat": "24.1791196",
            "Lng": "120.6489061"
        },
        {
            "magnitude": "52.507142371300304",
            "Lat": "24.1791086",
            "Lng": "120.6489178"
        },
        {
            "magnitude": "54.04627646748664",
            "Lat": "24.1790734",
            "Lng": "120.6489178"
        },
        {
            "magnitude": "38.22302970723278",
            "Lat": "24.1790467",
            "Lng": "120.6489226"
        },
        {
            "magnitude": "39.63584236521283",
            "Lat": "24.1790539",
            "Lng": "120.6488897"
        },
        {
            "magnitude": "48.63126566315131",
            "Lat": "24.1790527",
            "Lng": "120.648862"
        },
        {
            "magnitude": "49.13247398615299",
            "Lat": "24.1790461",
            "Lng": "120.6488205"
        },
        {
            "magnitude": "45.14421336118285",
            "Lat": "24.1790352",
            "Lng": "120.648809"
        },
        {
            "magnitude": "48.010415536631214",
            "Lat": "24.1790183",
            "Lng": "120.6487889"
        },
        {
            "magnitude": "47.54997371187496",
            "Lat": "24.1790101",
            "Lng": "120.6487665"
        },
        {
            "magnitude": "43.94314508543966",
            "Lat": "24.1789887",
            "Lng": "120.6487402"
        },
        {
            "magnitude": "45.95650117230423",
            "Lat": "24.1789794",
            "Lng": "120.6487288"
        },
        {
            "magnitude": "48.176757881783615",
            "Lat": "24.1789856",
            "Lng": "120.6486898"
        },
        {
            "magnitude": "48.176757881783615",
            "Lat": "24.1789856",
            "Lng": "120.6486898"
        },
        {
            "magnitude": "48.75448697299562",
            "Lat": "24.1789793",
            "Lng": "120.6486824"
        },
        {
            "magnitude": "48.75448697299562",
            "Lat": "24.1789793",
            "Lng": "120.6486824"
        },
        {
            "magnitude": "47.15930449020638",
            "Lat": "24.1789761",
            "Lng": "120.648676"
        },
        {
            "magnitude": "50.05996404313531",
            "Lat": "24.1789701",
            "Lng": "120.648663"
        },
        {
            "magnitude": "51.16639522186413",
            "Lat": "24.1789847",
            "Lng": "120.6486412"
        },
        {
            "magnitude": "47.89572005931219",
            "Lat": "24.1789973",
            "Lng": "120.6486178"
        },
        {
            "magnitude": "53.9351462406472",
            "Lat": "24.1789943",
            "Lng": "120.6486193"
        },
        {
            "magnitude": "54.00925846556311",
            "Lat": "24.1789693",
            "Lng": "120.6486103"
        },
        {
            "magnitude": "50.41825066382212",
            "Lat": "24.1789769",
            "Lng": "120.6485909"
        },
        {
            "magnitude": "52.81098370604357",
            "Lat": "24.1789735",
            "Lng": "120.6485872"
        },
        {
            "magnitude": "46.010868281309364",
            "Lat": "24.1788125",
            "Lng": "120.6476034"
        },
        {
            "magnitude": "45.12205669071391",
            "Lat": "24.178791",
            "Lng": "120.6475083"
        },
        {
            "magnitude": "44.06812907306141",
            "Lat": "24.1787928",
            "Lng": "120.6474958"
        },
        {
            "magnitude": "45.73838650411709",
            "Lat": "24.1787908",
            "Lng": "120.6474802"
        },
        {
            "magnitude": "43.657759905886145",
            "Lat": "24.1787953",
            "Lng": "120.6474641"
        },
        {
            "magnitude": "43.829214001622255",
            "Lat": "24.1787982",
            "Lng": "120.647444"
        },
        {
            "magnitude": "46.184412955021955",
            "Lat": "24.1787814",
            "Lng": "120.6474366"
        },
        {
            "magnitude": "38.52272056851645",
            "Lat": "24.1787907",
            "Lng": "120.6474231"
        },
        {
            "magnitude": "45.37620521815371",
            "Lat": "24.1787851",
            "Lng": "120.6474255"
        },
        {
            "magnitude": "43.977266854592045",
            "Lat": "24.1787941",
            "Lng": "120.6474261"
        },
        {
            "magnitude": "45.39823785126467",
            "Lat": "24.1787952",
            "Lng": "120.6474253"
        },
        {
            "magnitude": "44.86646854834911",
            "Lat": "24.1788046",
            "Lng": "120.6474126"
        },
        {
            "magnitude": "43.37049688440288",
            "Lat": "24.1788103",
            "Lng": "120.6474006"
        },
        {
            "magnitude": "46.861498055439924",
            "Lat": "24.1788049",
            "Lng": "120.6474006"
        },
        {
            "magnitude": "43.9203825119955",
            "Lat": "24.1788121",
            "Lng": "120.647388"
        },
        {
            "magnitude": "42.731721238442994",
            "Lat": "24.1788252",
            "Lng": "120.6473753"
        },
        {
            "magnitude": "43.60045871318328",
            "Lat": "24.1788393",
            "Lng": "120.6473538"
        },
        {
            "magnitude": "42.59107887809371",
            "Lat": "24.1788215",
            "Lng": "120.6473304"
        },
        {
            "magnitude": "43.93176527297759",
            "Lat": "24.1788115",
            "Lng": "120.6473134"
        },
        {
            "magnitude": "49.10193478876367",
            "Lat": "24.1787959",
            "Lng": "120.6472992"
        },
        {
            "magnitude": "47.80167361086848",
            "Lat": "24.1787598",
            "Lng": "120.6469932"
        },
        {
            "magnitude": "38.39270764090493",
            "Lat": "24.1787549",
            "Lng": "120.6469795"
        },
        {
            "magnitude": "38.39270764090493",
            "Lat": "24.1787549",
            "Lng": "120.6469795"
        },
        {
            "magnitude": "52.48809388804284",
            "Lat": "24.1789509",
            "Lng": "120.6469141"
        },
        {
            "magnitude": "48.84669896727925",
            "Lat": "24.1789398",
            "Lng": "120.6469358"
        },
        {
            "magnitude": "49.85980344927164",
            "Lat": "24.1789537",
            "Lng": "120.6469632"
        },
        {
            "magnitude": "49.4064773081425",
            "Lat": "24.1789323",
            "Lng": "120.6469543"
        },
        {
            "magnitude": "49.4064773081425",
            "Lat": "24.1789323",
            "Lng": "120.6469543"
        },
        {
            "magnitude": "49.82971001320397",
            "Lat": "24.1789234",
            "Lng": "120.6469678"
        },
        {
            "magnitude": "49.82971001320397",
            "Lat": "24.1789234",
            "Lng": "120.6469678"
        },
        {
            "magnitude": "47.97916214358062",
            "Lat": "24.1788743",
            "Lng": "120.6470109"
        },
        {
            "magnitude": "48.08326112068523",
            "Lat": "24.1788311",
            "Lng": "120.647017"
        },
        {
            "magnitude": "51.92301994298868",
            "Lat": "24.1788275",
            "Lng": "120.6470355"
        },
        {
            "magnitude": "51.92301994298868",
            "Lat": "24.1788215",
            "Lng": "120.6470266"
        },
        {
            "magnitude": "52.23983154643591",
            "Lat": "24.1788649",
            "Lng": "120.6470845"
        },
        {
            "magnitude": "52.23983154643591",
            "Lat": "24.1788683",
            "Lng": "120.6471046"
        },
        {
            "magnitude": "52.03844732503075",
            "Lat": "24.1788708",
            "Lng": "120.6471334"
        },
        {
            "magnitude": "52.54521862167861",
            "Lat": "24.1788697",
            "Lng": "120.6471419"
        },
        {
            "magnitude": "51.478150704935004",
            "Lat": "24.1788787",
            "Lng": "120.6471474"
        },
        {
            "magnitude": "51.93264869039514",
            "Lat": "24.1788856",
            "Lng": "120.6471611"
        },
        {
            "magnitude": "41.593268686170845",
            "Lat": "24.1789782",
            "Lng": "120.6473638"
        },
        {
            "magnitude": "42.37924020083418",
            "Lat": "24.1790523",
            "Lng": "120.6473651"
        },
        {
            "magnitude": "42.37924020083418",
            "Lat": "24.1790523",
            "Lng": "120.6473651"
        },
        {
            "magnitude": "41.53311931459037",
            "Lat": "24.1790659",
            "Lng": "120.6473563"
        },
        {
            "magnitude": "37.77565353504821",
            "Lat": "24.1790877",
            "Lng": "120.6473782"
        },
        {
            "magnitude": "37.77565353504821",
            "Lat": "24.1790877",
            "Lng": "120.6473782"
        },
        {
            "magnitude": "33.28663395418648",
            "Lat": "24.1805144",
            "Lng": "120.6462839"
        },
        {
            "magnitude": "41.53311931459037",
            "Lat": "24.1805096",
            "Lng": "120.6462818"
        },
        {
            "magnitude": "37.53664875824692",
            "Lat": "24.180513",
            "Lng": "120.6462822"
        },
        {
            "magnitude": "41.49698784249286",
            "Lat": "24.1805134",
            "Lng": "120.6462825"
        },
        {
            "magnitude": "53.49766350038102",
            "Lat": "24.1806947",
            "Lng": "120.6466514"
        },
        {
            "magnitude": "53.49766350038102",
            "Lat": "24.1806947",
            "Lng": "120.6466514"
        },
        {
            "magnitude": "53.85164807134504",
            "Lat": "24.180675",
            "Lng": "120.6466565"
        },
        {
            "magnitude": "48.692915295759406",
            "Lat": "24.1806717",
            "Lng": "120.6466688"
        },
        {
            "magnitude": "44.654227123532216",
            "Lat": "24.1806583",
            "Lng": "120.6467191"
        },
        {
            "magnitude": "38.50973902793941",
            "Lat": "24.1806742",
            "Lng": "120.6467499"
        },
        {
            "magnitude": "38.50973902793941",
            "Lat": "24.1806742",
            "Lng": "120.6467499"
        },
        {
            "magnitude": "49.72926703662542",
            "Lat": "24.1806846",
            "Lng": "120.6467836"
        },
        {
            "magnitude": "35.63705936241092",
            "Lat": "24.1806865",
            "Lng": "120.6468036"
        },
        {
            "magnitude": "42.731721238442994",
            "Lat": "24.180698",
            "Lng": "120.6468619"
        },
        {
            "magnitude": "42.731721238442994",
            "Lat": "24.180698",
            "Lng": "120.6468619"
        },
        {
            "magnitude": "38.01315561749642",
            "Lat": "24.1807018",
            "Lng": "120.6471964"
        },
        {
            "magnitude": "39.45883931389772",
            "Lat": "24.1807216",
            "Lng": "120.6472322"
        },
        {
            "magnitude": "42.95346318982906",
            "Lat": "24.1807157",
            "Lng": "120.6472774"
        },
        {
            "magnitude": "44.294469180700204",
            "Lat": "24.1806967",
            "Lng": "120.6472871"
        },
        {
            "magnitude": "44.294469180700204",
            "Lat": "24.1806967",
            "Lng": "120.6472871"
        },
        {
            "magnitude": "37.656340767525464",
            "Lat": "24.1806888",
            "Lng": "120.647293"
        },
        {
            "magnitude": "34.0147027033899",
            "Lat": "24.1806857",
            "Lng": "120.6473047"
        },
        {
            "magnitude": "43.243496620879306",
            "Lat": "24.180668",
            "Lng": "120.6473021"
        },
        {
            "magnitude": "41.340053217188775",
            "Lat": "24.1806589",
            "Lng": "120.6473042"
        },
        {
            "magnitude": "39.93745109543172",
            "Lat": "24.1806493",
            "Lng": "120.6473033"
        },
        {
            "magnitude": "39.35733730830886",
            "Lat": "24.1806389",
            "Lng": "120.6473089"
        },
        {
            "magnitude": "39.102429592034305",
            "Lat": "24.1806363",
            "Lng": "120.6473141"
        },
        {
            "magnitude": "38.91015291668744",
            "Lat": "24.1806285",
            "Lng": "120.6473161"
        },
        {
            "magnitude": "39.30648801406709",
            "Lat": "24.1806104",
            "Lng": "120.6473141"
        },
        {
            "magnitude": "39.1279950930277",
            "Lat": "24.1806091",
            "Lng": "120.6473198"
        },
        {
            "magnitude": "39.102429592034305",
            "Lat": "24.1805928",
            "Lng": "120.647318"
        },
        {
            "magnitude": "39.102429592034305",
            "Lat": "24.1805746",
            "Lng": "120.647315"
        },
        {
            "magnitude": "39.91240408695021",
            "Lat": "24.1805769",
            "Lng": "120.6473193"
        },
        {
            "magnitude": "38.961519477556315",
            "Lat": "24.18057",
            "Lng": "120.6473185"
        },
        {
            "magnitude": "40.45985664828782",
            "Lat": "24.1805626",
            "Lng": "120.6473165"
        },
        {
            "magnitude": "39.30648801406709",
            "Lat": "24.1805492",
            "Lng": "120.6473185"
        },
        {
            "magnitude": "39.319206502675",
            "Lat": "24.1805389",
            "Lng": "120.6473265"
        },
        {
            "magnitude": "35.9722114972099",
            "Lat": "24.1805277",
            "Lng": "120.6473339"
        },
        {
            "magnitude": "38.49675310984031",
            "Lat": "24.1805156",
            "Lng": "120.6473345"
        },
        {
            "magnitude": "34.07345007480164",
            "Lat": "24.1804997",
            "Lng": "120.647315"
        },
        {
            "magnitude": "35.24202037341219",
            "Lat": "24.1804869",
            "Lng": "120.6473176"
        },
        {
            "magnitude": "37.14835124201342",
            "Lat": "24.18047",
            "Lng": "120.6473092"
        },
        {
            "magnitude": "44.73253849269008",
            "Lat": "24.1798398",
            "Lng": "120.6499718"
        },
        {
            "magnitude": "41.617304093369626",
            "Lat": "24.1798393",
            "Lng": "120.6499958"
        },
        {
            "magnitude": "45.43126676640219",
            "Lat": "24.1798639",
            "Lng": "120.6500131"
        },
        {
            "magnitude": "39.761790704142086",
            "Lat": "24.1798638",
            "Lng": "120.6500228"
        },
        {
            "magnitude": "44.11349000022555",
            "Lat": "24.1799006",
            "Lng": "120.6500384"
        },
        {
            "magnitude": "47.50789408087881",
            "Lat": "24.1799073",
            "Lng": "120.650044"
        },
        {
            "magnitude": "46.33573135281238",
            "Lat": "24.1799127",
            "Lng": "120.6500505"
        },
        {
            "magnitude": "44.30575583375144",
            "Lat": "24.1799183",
            "Lng": "120.6500531"
        },
        {
            "magnitude": "33.391615714128",
            "Lat": "24.1798352",
            "Lng": "120.6500773"
        },
        {
            "magnitude": "33.391615714128",
            "Lat": "24.1798352",
            "Lng": "120.6500773"
        },
        {
            "magnitude": "30.870698080866262",
            "Lat": "24.1798061",
            "Lng": "120.6500735"
        },
        {
            "magnitude": "25.019992006393608",
            "Lat": "24.1797822",
            "Lng": "120.6500727"
        },
        {
            "magnitude": "42.8485705712571",
            "Lat": "24.1797478",
            "Lng": "120.650078"
        },
        {
            "magnitude": "44.384682042344295",
            "Lat": "24.1794081",
            "Lng": "120.650068"
        },
        {
            "magnitude": "34.72751070837067",
            "Lat": "24.1793668",
            "Lng": "120.6500754"
        },
        {
            "magnitude": "36.46916505762094",
            "Lat": "24.1793605",
            "Lng": "120.6500762"
        },
        {
            "magnitude": "35.24202037341219",
            "Lat": "24.1793621",
            "Lng": "120.6500726"
        },
        {
            "magnitude": "31.304951684997057",
            "Lat": "24.1793605",
            "Lng": "120.650074"
        },
        {
            "magnitude": "31.304951684997057",
            "Lat": "24.1793605",
            "Lng": "120.650074"
        },
        {
            "magnitude": "36.41428291206625",
            "Lat": "24.1793425",
            "Lng": "120.6500845"
        },
        {
            "magnitude": "37.376463182061514",
            "Lat": "24.1793229",
            "Lng": "120.6500928"
        },
        {
            "magnitude": "38.79432948254165",
            "Lat": "24.179317",
            "Lng": "120.6500872"
        },
        {
            "magnitude": "37.21558813185679",
            "Lat": "24.1793094",
            "Lng": "120.6500945"
        },
        {
            "magnitude": "34.49637662132068",
            "Lat": "24.1792956",
            "Lng": "120.6500908"
        },
        {
            "magnitude": "35.84689665786984",
            "Lat": "24.1792827",
            "Lng": "120.6500865"
        },
        {
            "magnitude": "34.26368339802363",
            "Lat": "24.1792616",
            "Lng": "120.6500854"
        },
        {
            "magnitude": "36.26292872893749",
            "Lat": "24.1792466",
            "Lng": "120.6500935"
        },
        {
            "magnitude": "37.26929030716845",
            "Lat": "24.1792344",
            "Lng": "120.6501004"
        },
        {
            "magnitude": "38.948684188300895",
            "Lat": "24.1792284",
            "Lng": "120.6500998"
        },
        {
            "magnitude": "38.948684188300895",
            "Lat": "24.1792284",
            "Lng": "120.6500998"
        },
        {
            "magnitude": "39.67366884975475",
            "Lat": "24.1789155",
            "Lng": "120.6500836"
        },
        {
            "magnitude": "38.19685850956856",
            "Lat": "24.1789273",
            "Lng": "120.6500889"
        },
        {
            "magnitude": "38.19685850956856",
            "Lat": "24.1789273",
            "Lng": "120.6500889"
        },
        {
            "magnitude": "39.1279950930277",
            "Lat": "24.1789094",
            "Lng": "120.6500986"
        },
        {
            "magnitude": "36.89173349139343",
            "Lat": "24.1789002",
            "Lng": "120.6501026"
        },
        {
            "magnitude": "41.41255848169731",
            "Lat": "24.1788859",
            "Lng": "120.6501011"
        },
        {
            "magnitude": "41.53311931459037",
            "Lat": "24.1788297",
            "Lng": "120.6500859"
        },
        {
            "magnitude": "40.162171256046406",
            "Lat": "24.1788172",
            "Lng": "120.6500865"
        },
        {
            "magnitude": "40.162171256046406",
            "Lat": "24.1788172",
            "Lng": "120.6500865"
        },
        {
            "magnitude": "41.701318923986086",
            "Lat": "24.1788013",
            "Lng": "120.6500924"
        },
        {
            "magnitude": "41.701318923986086",
            "Lat": "24.1788013",
            "Lng": "120.6500924"
        },
        {
            "magnitude": "42.731721238442994",
            "Lat": "24.1787658",
            "Lng": "120.650084"
        },
        {
            "magnitude": "43.23193264243457",
            "Lat": "24.1787579",
            "Lng": "120.6500738"
        },
        {
            "magnitude": "43.23193264243457",
            "Lat": "24.1787579",
            "Lng": "120.6500738"
        },
        {
            "magnitude": "42.24926034855522",
            "Lat": "24.1787201",
            "Lng": "120.6500734"
        },
        {
            "magnitude": "42.24926034855522",
            "Lat": "24.1787201",
            "Lng": "120.6500734"
        },
        {
            "magnitude": "39.824615503479755",
            "Lat": "24.1787107",
            "Lng": "120.6500688"
        },
        {
            "magnitude": "39.824615503479755",
            "Lat": "24.1787107",
            "Lng": "120.6500688"
        },
        {
            "magnitude": "48.36320915737499",
            "Lat": "24.1787561",
            "Lng": "120.6468723"
        },
        {
            "magnitude": "48.31148931672465",
            "Lat": "24.1787475",
            "Lng": "120.6468579"
        },
        {
            "magnitude": "48.31148931672465",
            "Lat": "24.1787475",
            "Lng": "120.6468579"
        },
        {
            "magnitude": "47.81213235152768",
            "Lat": "24.1787482",
            "Lng": "120.646847"
        },
        {
            "magnitude": "48.91829923454004",
            "Lat": "24.1787506",
            "Lng": "120.6468301"
        },
        {
            "magnitude": "48.91829923454004",
            "Lat": "24.1787506",
            "Lng": "120.6468301"
        },
        {
            "magnitude": "48.91829923454004",
            "Lat": "24.1787613",
            "Lng": "120.6468091"
        },
        {
            "magnitude": "48.86716689148246",
            "Lat": "24.1787514",
            "Lng": "120.6467935"
        },
        {
            "magnitude": "49.37610758251404",
            "Lat": "24.1787552",
            "Lng": "120.64678"
        },
        {
            "magnitude": "48.590122453025366",
            "Lat": "24.1787618",
            "Lng": "120.6467711"
        },
        {
            "magnitude": "48.590122453025366",
            "Lat": "24.1787618",
            "Lng": "120.6467711"
        },
        {
            "magnitude": "49.10193478876367",
            "Lat": "24.1787691",
            "Lng": "120.6467689"
        },
        {
            "magnitude": "49.50757517794625",
            "Lat": "24.1787686",
            "Lng": "120.6467535"
        },
        {
            "magnitude": "49.50757517794625",
            "Lat": "24.1787686",
            "Lng": "120.6467535"
        },
        {
            "magnitude": "49.9799959983992",
            "Lat": "24.178765",
            "Lng": "120.646738"
        },
        {
            "magnitude": "40.36087214122113",
            "Lat": "24.1788387",
            "Lng": "120.6466754"
        },
        {
            "magnitude": "43.94314508543966",
            "Lat": "24.1789352",
            "Lng": "120.6466455"
        },
        {
            "magnitude": "33.015148038438355",
            "Lat": "24.1795425",
            "Lng": "120.6465176"
        },
        {
            "magnitude": "32.71085446759225",
            "Lat": "24.1795511",
            "Lng": "120.646529"
        },
        {
            "magnitude": "43.174066289845804",
            "Lat": "24.1795616",
            "Lng": "120.6465236"
        },
        {
            "magnitude": "49.71921157862421",
            "Lat": "24.179588",
            "Lng": "120.6465165"
        },
        {
            "magnitude": "37.26929030716845",
            "Lat": "24.1796528",
            "Lng": "120.6464811"
        },
        {
            "magnitude": "37.26929030716845",
            "Lat": "24.1796528",
            "Lng": "120.6464811"
        },
        {
            "magnitude": "36.193922141707716",
            "Lat": "24.1796636",
            "Lng": "120.6464787"
        },
        {
            "magnitude": "50.695167422546305",
            "Lat": "24.1796861",
            "Lng": "120.6464682"
        },
        {
            "magnitude": "38.58756276314948",
            "Lat": "24.1796963",
            "Lng": "120.6464555"
        },
        {
            "magnitude": "47.968739820845826",
            "Lat": "24.1800208",
            "Lng": "120.6465327"
        },
        {
            "magnitude": "37.54996671103717",
            "Lat": "24.180026",
            "Lng": "120.6465307"
        },
        {
            "magnitude": "33.793490497431605",
            "Lat": "24.1800289",
            "Lng": "120.6465291"
        },
        {
            "magnitude": "30.870698080866262",
            "Lat": "24.1800387",
            "Lng": "120.6465229"
        },
        {
            "magnitude": "37.76241517699841",
            "Lat": "24.1800458",
            "Lng": "120.6465234"
        },
        {
            "magnitude": "50.22947341949744",
            "Lat": "24.1800685",
            "Lng": "120.6465213"
        },
        {
            "magnitude": "37.027017163147235",
            "Lat": "24.1800993",
            "Lng": "120.6465246"
        },
        {
            "magnitude": "32.28002478313795",
            "Lat": "24.1801068",
            "Lng": "120.6465182"
        },
        {
            "magnitude": "31.400636936215164",
            "Lat": "24.1801153",
            "Lng": "120.6465138"
        },
        {
            "magnitude": "33.734255586866",
            "Lat": "24.1801227",
            "Lng": "120.6465178"
        },
        {
            "magnitude": "42.2965719651132",
            "Lat": "24.1801289",
            "Lng": "120.6465056"
        },
        {
            "magnitude": "37.70941526992961",
            "Lat": "24.1801345",
            "Lng": "120.6465003"
        },
        {
            "magnitude": "35.482389998420345",
            "Lat": "24.1801484",
            "Lng": "120.646507"
        },
        {
            "magnitude": "33.19638534539566",
            "Lat": "24.1801526",
            "Lng": "120.6464838"
        },
        {
            "magnitude": "32.14031735997639",
            "Lat": "24.180157",
            "Lng": "120.6464854"
        },
        {
            "magnitude": "41.96427051671457",
            "Lat": "24.1801576",
            "Lng": "120.6464618"
        },
        {
            "magnitude": "42.30839160261236",
            "Lat": "24.1801748",
            "Lng": "120.6464741"
        },
        {
            "magnitude": "35.185224171518364",
            "Lat": "24.1801778",
            "Lng": "120.6464664"
        },
        {
            "magnitude": "30.805843601498726",
            "Lat": "24.1801843",
            "Lng": "120.6464753"
        },
        {
            "magnitude": "28.460498941515414",
            "Lat": "24.1792688",
            "Lng": "120.6493936"
        },
        {
            "magnitude": "28.372521918222215",
            "Lat": "24.1792699",
            "Lng": "120.6493935"
        },
        {
            "magnitude": "32.264531609803356",
            "Lat": "24.1792707",
            "Lng": "120.6493935"
        },
        {
            "magnitude": "32.264531609803356",
            "Lat": "24.1792719",
            "Lng": "120.6493933"
        },
        {
            "magnitude": "32.77193921634788",
            "Lat": "24.1792727",
            "Lng": "120.6493937"
        },
        {
            "magnitude": "32.77193921634788",
            "Lat": "24.1792727",
            "Lng": "120.6493941"
        },
        {
            "magnitude": "32.77193921634788",
            "Lat": "24.1792728",
            "Lng": "120.6493949"
        },
        {
            "magnitude": "32.77193921634788",
            "Lat": "24.1792737",
            "Lng": "120.649395"
        },
        {
            "magnitude": "32.77193921634788",
            "Lat": "24.1792744",
            "Lng": "120.6493952"
        },
        {
            "magnitude": "32.77193921634788",
            "Lat": "24.1792748",
            "Lng": "120.6493953"
        },
        {
            "magnitude": "32.77193921634788",
            "Lat": "24.1792752",
            "Lng": "120.6493954"
        },
        {
            "magnitude": "32.77193921634788",
            "Lat": "24.1792747",
            "Lng": "120.649396"
        },
        {
            "magnitude": "32.77193921634788",
            "Lat": "24.1792768",
            "Lng": "120.6493963"
        },
        {
            "magnitude": "32.77193921634788",
            "Lat": "24.1792766",
            "Lng": "120.6493964"
        },
        {
            "magnitude": "33.13608305156178",
            "Lat": "24.1792768",
            "Lng": "120.6493963"
        },
        {
            "magnitude": "32.78719262151",
            "Lat": "24.1792769",
            "Lng": "120.6493961"
        },
        {
            "magnitude": "33.18132004607411",
            "Lat": "24.1792764",
            "Lng": "120.6493962"
        },
        {
            "magnitude": "34.785054261852174",
            "Lat": "24.1792758",
            "Lng": "120.6493965"
        },
        {
            "magnitude": "32.984845004941285",
            "Lat": "24.1792755",
            "Lng": "120.649397"
        },
        {
            "magnitude": "32.984845004941285",
            "Lat": "24.1792754",
            "Lng": "120.6493974"
        },
        {
            "magnitude": "32.984845004941285",
            "Lat": "24.1792777",
            "Lng": "120.6493968"
        },
        {
            "magnitude": "33.12099032335839",
            "Lat": "24.1792801",
            "Lng": "120.6493958"
        },
        {
            "magnitude": "33.74907406137241",
            "Lat": "24.1792823",
            "Lng": "120.6493949"
        },
        {
            "magnitude": "33.67491648096547",
            "Lat": "24.179284",
            "Lng": "120.6493941"
        },
        {
            "magnitude": "32.31098884280702",
            "Lat": "24.179283",
            "Lng": "120.6493945"
        },
        {
            "magnitude": "32.38826948140329",
            "Lat": "24.179282",
            "Lng": "120.6493948"
        },
        {
            "magnitude": "32.31098884280702",
            "Lat": "24.1792811",
            "Lng": "120.649395"
        },
        {
            "magnitude": "33.18132004607411",
            "Lat": "24.1792804",
            "Lng": "120.6493951"
        },
        {
            "magnitude": "32.31098884280702",
            "Lat": "24.1792801",
            "Lng": "120.6493951"
        },
        {
            "magnitude": "32.31098884280702",
            "Lat": "24.1792803",
            "Lng": "120.6493947"
        },
        {
            "magnitude": "32.38826948140329",
            "Lat": "24.1792803",
            "Lng": "120.6493946"
        },
        {
            "magnitude": "32.817678162843876",
            "Lat": "24.1792804",
            "Lng": "120.6493945"
        },
        {
            "magnitude": "32.31098884280702",
            "Lat": "24.1792801",
            "Lng": "120.6493946"
        },
        {
            "magnitude": "32.817678162843876",
            "Lat": "24.1792794",
            "Lng": "120.6493949"
        },
        {
            "magnitude": "32.31098884280702",
            "Lat": "24.1792785",
            "Lng": "120.6493953"
        },
        {
            "magnitude": "32.71085446759225",
            "Lat": "24.1792783",
            "Lng": "120.6493955"
        },
        {
            "magnitude": "45.02221673796171",
            "Lat": "24.1792781",
            "Lng": "120.6493959"
        },
        {
            "magnitude": "44.11349000022555",
            "Lat": "24.179278",
            "Lng": "120.6493961"
        },
        {
            "magnitude": "40.64480286580315",
            "Lat": "24.179278",
            "Lng": "120.6493962"
        },
        {
            "magnitude": "40.85339643163099",
            "Lat": "24.1792777",
            "Lng": "120.6493963"
        },
        {
            "magnitude": "41.15823125451335",
            "Lat": "24.1792772",
            "Lng": "120.6493964"
        },
        {
            "magnitude": "41.15823125451335",
            "Lat": "24.179277",
            "Lng": "120.6493961"
        },
        {
            "magnitude": "42.579337712087536",
            "Lat": "24.1792769",
            "Lng": "120.6493963"
        },
        {
            "magnitude": "42.02380277890139",
            "Lat": "24.1792766",
            "Lng": "120.6493964"
        },
        {
            "magnitude": "42.579337712087536",
            "Lat": "24.1792766",
            "Lng": "120.6493963"
        },
        {
            "magnitude": "42.02380277890139",
            "Lat": "24.1792767",
            "Lng": "120.649396"
        },
        {
            "magnitude": "42.83689998120779",
            "Lat": "24.1792771",
            "Lng": "120.6493956"
        },
        {
            "magnitude": "42.579337712087536",
            "Lat": "24.1792773",
            "Lng": "120.6493952"
        },
        {
            "magnitude": "42.579337712087536",
            "Lat": "24.1792772",
            "Lng": "120.6493953"
        },
        {
            "magnitude": "42.579337712087536",
            "Lat": "24.1792768",
            "Lng": "120.6493956"
        },
        {
            "magnitude": "40.422765862815474",
            "Lat": "24.1792768",
            "Lng": "120.6493956"
        },
        {
            "magnitude": "41.12177038990418",
            "Lat": "24.1792769",
            "Lng": "120.6493954"
        },
        {
            "magnitude": "43.68065933568311",
            "Lat": "24.1792846",
            "Lng": "120.6493882"
        },
        {
            "magnitude": "52.66877632905477",
            "Lat": "24.1792869",
            "Lng": "120.6493861"
        },
        {
            "magnitude": "50.48762224545735",
            "Lat": "24.1793006",
            "Lng": "120.6493724"
        },
        {
            "magnitude": "50.17967716117751",
            "Lat": "24.1793217",
            "Lng": "120.6493645"
        },
        {
            "magnitude": "50.76416058598822",
            "Lat": "24.1793585",
            "Lng": "120.6493466"
        },
        {
            "magnitude": "50.724747411889595",
            "Lat": "24.1793457",
            "Lng": "120.6493539"
        },
        {
            "magnitude": "49.759421218498915",
            "Lat": "24.1793325",
            "Lng": "120.6493633"
        },
        {
            "magnitude": "49.658836071740545",
            "Lat": "24.1793296",
            "Lng": "120.6493645"
        },
        {
            "magnitude": "48.98979485566356",
            "Lat": "24.1793276",
            "Lng": "120.6493656"
        },
        {
            "magnitude": "48.86716689148246",
            "Lat": "24.1793212",
            "Lng": "120.6493709"
        },
        {
            "magnitude": "56.789083458002736",
            "Lat": "24.1793215",
            "Lng": "120.6493703"
        },
        {
            "magnitude": "49.28488612140643",
            "Lat": "24.1793174",
            "Lng": "120.6493714"
        },
        {
            "magnitude": "63.079315151640635",
            "Lat": "24.1793094",
            "Lng": "120.6493765"
        },
        {
            "magnitude": "63.3798075099633",
            "Lat": "24.1793029",
            "Lng": "120.6493796"
        },
        {
            "magnitude": "63.53739056650029",
            "Lat": "24.179298",
            "Lng": "120.6493818"
        },
        {
            "magnitude": "64.10928169929842",
            "Lat": "24.1792935",
            "Lng": "120.6493837"
        },
        {
            "magnitude": "63.53739056650029",
            "Lat": "24.1792923",
            "Lng": "120.6493853"
        },
        {
            "magnitude": "63.53739056650029",
            "Lat": "24.1792913",
            "Lng": "120.6493864"
        },
        {
            "magnitude": "58.86425061104575",
            "Lat": "24.1792887",
            "Lng": "120.6493879"
        },
        {
            "magnitude": "60.30754513325841",
            "Lat": "24.1792863",
            "Lng": "120.6493893"
        },
        {
            "magnitude": "60.30754513325841",
            "Lat": "24.1792844",
            "Lng": "120.6493904"
        },
        {
            "magnitude": "61.554853586049575",
            "Lat": "24.1792835",
            "Lng": "120.649391"
        },
        {
            "magnitude": "53.41348144429457",
            "Lat": "24.179282",
            "Lng": "120.6493919"
        },
        {
            "magnitude": "54.230987451824994",
            "Lat": "24.1792808",
            "Lng": "120.6493924"
        },
        {
            "magnitude": "54.46099521676041",
            "Lat": "24.1792799",
            "Lng": "120.6493929"
        },
        {
            "magnitude": "53.291650377896914",
            "Lat": "24.1792794",
            "Lng": "120.6493918"
        },
        {
            "magnitude": "53.52569476429054",
            "Lat": "24.1792795",
            "Lng": "120.6493908"
        },
        {
            "magnitude": "53.27288240746881",
            "Lat": "24.1792793",
            "Lng": "120.6493903"
        },
        {
            "magnitude": "43.104524124504614",
            "Lat": "24.1792787",
            "Lng": "120.6493913"
        },
        {
            "magnitude": "42.74342054632502",
            "Lat": "24.1792782",
            "Lng": "120.6493929"
        },
        {
            "magnitude": "43.32435804486894",
            "Lat": "24.1792772",
            "Lng": "120.6493954"
        },
        {
            "magnitude": "43.104524124504614",
            "Lat": "24.1792767",
            "Lng": "120.6493964"
        },
        {
            "magnitude": "43.104524124504614",
            "Lat": "24.1792771",
            "Lng": "120.649396"
        },
        {
            "magnitude": "43.104524124504614",
            "Lat": "24.1792771",
            "Lng": "120.6493957"
        },
        {
            "magnitude": "43.104524124504614",
            "Lat": "24.1792773",
            "Lng": "120.6493956"
        },
        {
            "magnitude": "43.485629810317796",
            "Lat": "24.1792773",
            "Lng": "120.6493958"
        },
        {
            "magnitude": "43.104524124504614",
            "Lat": "24.1792776",
            "Lng": "120.6493959"
        },
        {
            "magnitude": "42.20189569201838",
            "Lat": "24.1792777",
            "Lng": "120.6493964"
        },
        {
            "magnitude": "43.104524124504614",
            "Lat": "24.1792801",
            "Lng": "120.6493944"
        },
        {
            "magnitude": "42.74342054632502",
            "Lat": "24.1792837",
            "Lng": "120.6493918"
        },
        {
            "magnitude": "42.74342054632502",
            "Lat": "24.1792891",
            "Lng": "120.649389"
        },
        {
            "magnitude": "43.104524124504614",
            "Lat": "24.1792935",
            "Lng": "120.6493868"
        },
        {
            "magnitude": "43.32435804486894",
            "Lat": "24.1792946",
            "Lng": "120.6493871"
        },
        {
            "magnitude": "42.5440947723653",
            "Lat": "24.1792947",
            "Lng": "120.6493875"
        },
        {
            "magnitude": "42.906875905849866",
            "Lat": "24.1792946",
            "Lng": "120.6493879"
        },
        {
            "magnitude": "41.83300132670378",
            "Lat": "24.1792914",
            "Lng": "120.6493897"
        },
        {
            "magnitude": "42.96510211788167",
            "Lat": "24.1792881",
            "Lng": "120.6493915"
        },
        {
            "magnitude": "43.32435804486894",
            "Lat": "24.1792785",
            "Lng": "120.6493964"
        },
        {
            "magnitude": "43.104524124504614",
            "Lat": "24.17928",
            "Lng": "120.649397"
        },
        {
            "magnitude": "43.104524124504614",
            "Lat": "24.17928",
            "Lng": "120.649397"
        },
        {
            "magnitude": "42.74342054632502",
            "Lat": "24.1792816",
            "Lng": "120.6493971"
        },
        {
            "magnitude": "42.906875905849866",
            "Lat": "24.1792828",
            "Lng": "120.6493973"
        },
        {
            "magnitude": "43.81780460041329",
            "Lat": "24.1792835",
            "Lng": "120.6493975"
        },
        {
            "magnitude": "43.104524124504614",
            "Lat": "24.1792841",
            "Lng": "120.6493974"
        },
        {
            "magnitude": "43.104524124504614",
            "Lat": "24.1792832",
            "Lng": "120.6493969"
        },
        {
            "magnitude": "43.104524124504614",
            "Lat": "24.1792828",
            "Lng": "120.6493962"
        },
        {
            "magnitude": "43.104524124504614",
            "Lat": "24.1792828",
            "Lng": "120.6493958"
        },
        {
            "magnitude": "42.74342054632502",
            "Lat": "24.1792826",
            "Lng": "120.6493956"
        },
        {
            "magnitude": "43.104524124504614",
            "Lat": "24.1792825",
            "Lng": "120.6493955"
        },
        {
            "magnitude": "42.74342054632502",
            "Lat": "24.1792823",
            "Lng": "120.6493955"
        },
        {
            "magnitude": "43.104524124504614",
            "Lat": "24.1792823",
            "Lng": "120.6493953"
        },
        {
            "magnitude": "43.104524124504614",
            "Lat": "24.1792821",
            "Lng": "120.649395"
        },
        {
            "magnitude": "43.104524124504614",
            "Lat": "24.1792818",
            "Lng": "120.6493951"
        },
        {
            "magnitude": "43.104524124504614",
            "Lat": "24.1792809",
            "Lng": "120.6493953"
        },
        {
            "magnitude": "43.104524124504614",
            "Lat": "24.1792805",
            "Lng": "120.6493953"
        },
        {
            "magnitude": "43.104524124504614",
            "Lat": "24.1792804",
            "Lng": "120.6493951"
        },
        {
            "magnitude": "43.104524124504614",
            "Lat": "24.1792797",
            "Lng": "120.6493954"
        },
        {
            "magnitude": "43.104524124504614",
            "Lat": "24.1792788",
            "Lng": "120.6493957"
        },
        {
            "magnitude": "42.74342054632502",
            "Lat": "24.179278",
            "Lng": "120.6493958"
        },
        {
            "magnitude": "43.104524124504614",
            "Lat": "24.1792779",
            "Lng": "120.6493956"
        },
        {
            "magnitude": "42.74342054632502",
            "Lat": "24.1792777",
            "Lng": "120.6493955"
        },
        {
            "magnitude": "42.74342054632502",
            "Lat": "24.1792774",
            "Lng": "120.6493957"
        },
        {
            "magnitude": "43.104524124504614",
            "Lat": "24.1792773",
            "Lng": "120.6493958"
        },
        {
            "magnitude": "43.104524124504614",
            "Lat": "24.1792801",
            "Lng": "120.6493946"
        },
        {
            "magnitude": "42.74342054632502",
            "Lat": "24.1792799",
            "Lng": "120.6493946"
        },
        {
            "magnitude": "43.32435804486894",
            "Lat": "24.1792797",
            "Lng": "120.6493947"
        },
        {
            "magnitude": "43.104524124504614",
            "Lat": "24.1792793",
            "Lng": "120.6493948"
        },
        {
            "magnitude": "42.96510211788167",
            "Lat": "24.1792783",
            "Lng": "120.6493954"
        },
        {
            "magnitude": "43.32435804486894",
            "Lat": "24.1792775",
            "Lng": "120.649396"
        },
        {
            "magnitude": "41.15823125451335",
            "Lat": "24.1792768",
            "Lng": "120.6493965"
        },
        {
            "magnitude": "41.20679555607303",
            "Lat": "24.1792764",
            "Lng": "120.6493971"
        },
        {
            "magnitude": "40.90232267243512",
            "Lat": "24.1792753",
            "Lng": "120.649398"
        },
        {
            "magnitude": "41.012193308819754",
            "Lat": "24.1792749",
            "Lng": "120.6493984"
        },
        {
            "magnitude": "55.68662316930342",
            "Lat": "24.1792744",
            "Lng": "120.6493987"
        },
        {
            "magnitude": "35.185224171518364",
            "Lat": "24.1792744",
            "Lng": "120.6493984"
        },
        {
            "magnitude": "50.566787519082126",
            "Lat": "24.1792747",
            "Lng": "120.6493978"
        },
        {
            "magnitude": "49.21381919745713",
            "Lat": "24.1792968",
            "Lng": "120.6493877"
        },
        {
            "magnitude": "47.81213235152768",
            "Lat": "24.1792937",
            "Lng": "120.6493865"
        },
        {
            "magnitude": "48.010415536631214",
            "Lat": "24.1792938",
            "Lng": "120.6493865"
        },
        {
            "magnitude": "50.299105359837164",
            "Lat": "24.1792921",
            "Lng": "120.6493883"
        },
        {
            "magnitude": "53.600373133029585",
            "Lat": "24.1792919",
            "Lng": "120.6493885"
        },
        {
            "magnitude": "45.902069670114",
            "Lat": "24.1792917",
            "Lng": "120.6493886"
        },
        {
            "magnitude": "34.19064199455752",
            "Lat": "24.1792968",
            "Lng": "120.6493858"
        },
        {
            "magnitude": "40.311288741492746",
            "Lat": "24.1793033",
            "Lng": "120.6493821"
        },
        {
            "magnitude": "36.27671429443411",
            "Lat": "24.1793311",
            "Lng": "120.6493661"
        },
        {
            "magnitude": "35.958309192730404",
            "Lat": "24.1793284",
            "Lng": "120.6493627"
        },
        {
            "magnitude": "42.07136793592526",
            "Lat": "24.1793103",
            "Lng": "120.6493776"
        },
        {
            "magnitude": "37.749172176353746",
            "Lat": "24.1793043",
            "Lng": "120.6493825"
        },
        {
            "magnitude": "39.06404996924922",
            "Lat": "24.1793005",
            "Lng": "120.6493834"
        },
        {
            "magnitude": "47.686476070265456",
            "Lat": "24.1793643",
            "Lng": "120.6493449"
        },
        {
            "magnitude": "35.62302626111375",
            "Lat": "24.1794031",
            "Lng": "120.6493193"
        },
        {
            "magnitude": "37.456641600656084",
            "Lat": "24.1794226",
            "Lng": "120.6492968"
        },
        {
            "magnitude": "42.24926034855522",
            "Lat": "24.1794196",
            "Lng": "120.6492644"
        },
        {
            "magnitude": "39.72404813208241",
            "Lat": "24.179421",
            "Lng": "120.6492436"
        },
        {
            "magnitude": "35.79106033634656",
            "Lat": "24.1794301",
            "Lng": "120.6492454"
        },
        {
            "magnitude": "44.02272140611028",
            "Lat": "24.1794248",
            "Lng": "120.6492341"
        },
        {
            "magnitude": "35.63705936241092",
            "Lat": "24.1794267",
            "Lng": "120.6492308"
        },
        {
            "magnitude": "33.85262175962151",
            "Lat": "24.179429",
            "Lng": "120.6492183"
        },
        {
            "magnitude": "52.64978632435273",
            "Lat": "24.179432",
            "Lng": "120.6492095"
        },
        {
            "magnitude": "43.68065933568311",
            "Lat": "24.1794401",
            "Lng": "120.649209"
        },
        {
            "magnitude": "46.05431575867782",
            "Lat": "24.17939",
            "Lng": "120.6491481"
        },
        {
            "magnitude": "42.555845661906424",
            "Lat": "24.1793964",
            "Lng": "120.649096"
        },
        {
            "magnitude": "47.56048780237646",
            "Lat": "24.179558",
            "Lng": "120.6489535"
        },
        {
            "magnitude": "44.87761134463375",
            "Lat": "24.1795242",
            "Lng": "120.6489422"
        },
        {
            "magnitude": "43.86342439892262",
            "Lat": "24.1795299",
            "Lng": "120.6489281"
        },
        {
            "magnitude": "43.79497688091638",
            "Lat": "24.1795565",
            "Lng": "120.6489188"
        },
        {
            "magnitude": "45.628938186199335",
            "Lat": "24.1795611",
            "Lng": "120.6488999"
        },
        {
            "magnitude": "44.87761134463375",
            "Lat": "24.1795681",
            "Lng": "120.6489072"
        },
        {
            "magnitude": "45.65084884205331",
            "Lat": "24.1795591",
            "Lng": "120.6489305"
        },
        {
            "magnitude": "46.09772228646444",
            "Lat": "24.1795635",
            "Lng": "120.6489366"
        },
        {
            "magnitude": "45.81484475582123",
            "Lat": "24.1795545",
            "Lng": "120.6489532"
        },
        {
            "magnitude": "46.2709412050371",
            "Lat": "24.1795648",
            "Lng": "120.6489565"
        },
        {
            "magnitude": "44.48595283907045",
            "Lat": "24.1795633",
            "Lng": "120.6489711"
        },
        {
            "magnitude": "46.70117771534247",
            "Lat": "24.1795647",
            "Lng": "120.6489718"
        },
        {
            "magnitude": "47.36032094485847",
            "Lat": "24.1795645",
            "Lng": "120.6489791"
        },
        {
            "magnitude": "45.67274898667694",
            "Lat": "24.1795654",
            "Lng": "120.6489816"
        },
        {
            "magnitude": "48.46648326421054",
            "Lat": "24.179569",
            "Lng": "120.648987"
        },
        {
            "magnitude": "36.78314831549904",
            "Lat": "24.1792705",
            "Lng": "120.6493699"
        },
        {
            "magnitude": "31.78049716414141",
            "Lat": "24.1793212",
            "Lng": "120.6493914"
        },
        {
            "magnitude": "40.13726448077895",
            "Lat": "24.1793687",
            "Lng": "120.6494177"
        },
        {
            "magnitude": "28.948229652260256",
            "Lat": "24.1793975",
            "Lng": "120.6494195"
        },
        {
            "magnitude": "28.071337695236398",
            "Lat": "24.1794227",
            "Lng": "120.6493929"
        },
        {
            "magnitude": "33.63034344160047",
            "Lat": "24.1794274",
            "Lng": "120.649401"
        },
        {
            "magnitude": "40.07492981902776",
            "Lat": "24.1793831",
            "Lng": "120.6493955"
        },
        {
            "magnitude": "237.75828061289474",
            "Lat": "24.1793343",
            "Lng": "120.6493927"
        },
        {
            "magnitude": "229.30329260610281",
            "Lat": "24.1793075",
            "Lng": "120.6493934"
        },
        {
            "magnitude": "49.52776998815917",
            "Lat": "24.1792989",
            "Lng": "120.6493937"
        },
        {
            "magnitude": "53.637673327615545",
            "Lat": "24.1792754",
            "Lng": "120.6493971"
        },
        {
            "magnitude": "53.637673327615545",
            "Lat": "24.1792754",
            "Lng": "120.6493971"
        },
        {
            "magnitude": "52.88667128870941",
            "Lat": "24.1792755",
            "Lng": "120.6493973"
        },
        {
            "magnitude": "52.88667128870941",
            "Lat": "24.1792755",
            "Lng": "120.6493973"
        },
        {
            "magnitude": "52.88667128870941",
            "Lat": "24.1792757",
            "Lng": "120.6493972"
        },
        {
            "magnitude": "52.88667128870941",
            "Lat": "24.1792757",
            "Lng": "120.6493972"
        },
        {
            "magnitude": "53.68426212587819",
            "Lat": "24.1792782",
            "Lng": "120.6493964"
        },
        {
            "magnitude": "53.68426212587819",
            "Lat": "24.1792782",
            "Lng": "120.6493964"
        },
        {
            "magnitude": "52.88667128870941",
            "Lat": "24.1792783",
            "Lng": "120.6493963"
        },
        {
            "magnitude": "52.88667128870941",
            "Lat": "24.1792783",
            "Lng": "120.6493963"
        },
        {
            "magnitude": "57.01754116059373",
            "Lat": "24.179278",
            "Lng": "120.6493966"
        },
        {
            "magnitude": "57.01754116059373",
            "Lat": "24.179278",
            "Lng": "120.6493966"
        },
        {
            "magnitude": "60.14149981501958",
            "Lat": "24.179278",
            "Lng": "120.6493967"
        },
        {
            "magnitude": "60.14149981501958",
            "Lat": "24.179278",
            "Lng": "120.6493967"
        },
        {
            "magnitude": "39.8622628559895",
            "Lat": "24.179278",
            "Lng": "120.6493964"
        },
        {
            "magnitude": "40.311288741492746",
            "Lat": "24.179278",
            "Lng": "120.6493964"
        },
        {
            "magnitude": "39.57271787481876",
            "Lat": "24.1793007",
            "Lng": "120.6493834"
        },
        {
            "magnitude": "39.57271787481876",
            "Lat": "24.1793007",
            "Lng": "120.6493834"
        },
        {
            "magnitude": "36.41428291206625",
            "Lat": "24.179321",
            "Lng": "120.6493729"
        },
        {
            "magnitude": "36.41428291206625",
            "Lat": "24.179321",
            "Lng": "120.6493729"
        },
        {
            "magnitude": "38.06573262134856",
            "Lat": "24.1793379",
            "Lng": "120.6493641"
        },
        {
            "magnitude": "38.06573262134856",
            "Lat": "24.1793379",
            "Lng": "120.6493641"
        },
        {
            "magnitude": "37.8549864614954",
            "Lat": "24.1793514",
            "Lng": "120.6493565"
        },
        {
            "magnitude": "37.8549864614954",
            "Lat": "24.1793514",
            "Lng": "120.6493565"
        },
        {
            "magnitude": "30.886890422961002",
            "Lat": "24.179423",
            "Lng": "120.649237"
        },
        {
            "magnitude": "30.886890422961002",
            "Lat": "24.179423",
            "Lng": "120.649237"
        },
        {
            "magnitude": "38.84584919911006",
            "Lat": "24.179425",
            "Lng": "120.6492453"
        },
        {
            "magnitude": "38.84584919911006",
            "Lat": "24.179425",
            "Lng": "120.6492453"
        },
        {
            "magnitude": "38.84584919911006",
            "Lat": "24.179425",
            "Lng": "120.6492453"
        },
        {
            "magnitude": "31.591137997862628",
            "Lat": "24.1794338",
            "Lng": "120.6492662"
        },
        {
            "magnitude": "31.591137997862628",
            "Lat": "24.1794338",
            "Lng": "120.6492662"
        },
        {
            "magnitude": "33.91164991562634",
            "Lat": "24.1794349",
            "Lng": "120.6492769"
        },
        {
            "magnitude": "33.91164991562634",
            "Lat": "24.1794349",
            "Lng": "120.6492769"
        },
        {
            "magnitude": "28.442925306655784",
            "Lat": "24.1794314",
            "Lng": "120.6492759"
        },
        {
            "magnitude": "28.442925306655784",
            "Lat": "24.1794314",
            "Lng": "120.6492759"
        },
        {
            "magnitude": "53.27288240746881",
            "Lat": "24.1797637",
            "Lng": "120.6486862"
        },
        {
            "magnitude": "53.018864567246254",
            "Lat": "24.1797637",
            "Lng": "120.6486862"
        },
        {
            "magnitude": "51.56549233741495",
            "Lat": "24.1797642",
            "Lng": "120.6486857"
        },
        {
            "magnitude": "51.56549233741495",
            "Lat": "24.1797642",
            "Lng": "120.6486857"
        },
        {
            "magnitude": "47.92702786528704",
            "Lat": "24.179765",
            "Lng": "120.648686"
        },
        {
            "magnitude": "47.92702786528704",
            "Lat": "24.179765",
            "Lng": "120.648686"
        },
        {
            "magnitude": "54.89080068645383",
            "Lat": "24.1797653",
            "Lng": "120.6486862"
        },
        {
            "magnitude": "54.89080068645383",
            "Lat": "24.1797653",
            "Lng": "120.6486862"
        },
        {
            "magnitude": "55.80322571321482",
            "Lat": "24.1797653",
            "Lng": "120.6486861"
        },
        {
            "magnitude": "55.80322571321482",
            "Lat": "24.1797653",
            "Lng": "120.6486861"
        },
        {
            "magnitude": "13.96424004376894",
            "Lat": "24.1797673",
            "Lng": "120.6486917"
        },
        {
            "magnitude": "13.96424004376894",
            "Lat": "24.1797673",
            "Lng": "120.6486917"
        },
        {
            "magnitude": "43.79497688091638",
            "Lat": "24.1797773",
            "Lng": "120.6487024"
        },
        {
            "magnitude": "43.79497688091638",
            "Lat": "24.1797773",
            "Lng": "120.6487024"
        },
        {
            "magnitude": "69.32532004974806",
            "Lat": "24.1797712",
            "Lng": "120.6486944"
        },
        {
            "magnitude": "69.32532004974806",
            "Lat": "24.1797712",
            "Lng": "120.6486944"
        },
        {
            "magnitude": "51.778373863998475",
            "Lat": "24.1797683",
            "Lng": "120.6486905"
        },
        {
            "magnitude": "51.778373863998475",
            "Lat": "24.1797683",
            "Lng": "120.6486905"
        },
        {
            "magnitude": "37.05401462729781",
            "Lat": "24.1797666",
            "Lng": "120.6486881"
        },
        {
            "magnitude": "37.05401462729781",
            "Lat": "24.1797666",
            "Lng": "120.6486881"
        },
        {
            "magnitude": "22.67156809750927",
            "Lat": "24.1797599",
            "Lng": "120.6486862"
        },
        {
            "magnitude": "22.67156809750927",
            "Lat": "24.1797599",
            "Lng": "120.6486862"
        },
        {
            "magnitude": "29.223278392404914",
            "Lat": "24.179756",
            "Lng": "120.6486858"
        },
        {
            "magnitude": "29.223278392404914",
            "Lat": "24.179756",
            "Lng": "120.6486858"
        },
        {
            "magnitude": "39.761790704142086",
            "Lat": "24.1797539",
            "Lng": "120.6486854"
        },
        {
            "magnitude": "39.761790704142086",
            "Lat": "24.1797539",
            "Lng": "120.6486854"
        },
        {
            "magnitude": "36.46916505762094",
            "Lat": "24.1797632",
            "Lng": "120.6486877"
        },
        {
            "magnitude": "36.46916505762094",
            "Lat": "24.1797632",
            "Lng": "120.6486877"
        },
        {
            "magnitude": "31.843366656181317",
            "Lat": "24.179766",
            "Lng": "120.6486917"
        },
        {
            "magnitude": "31.843366656181317",
            "Lat": "24.179766",
            "Lng": "120.6486917"
        },
        {
            "magnitude": "32.78719262151",
            "Lat": "24.1797652",
            "Lng": "120.6486882"
        },
        {
            "magnitude": "32.78719262151",
            "Lat": "24.1797652",
            "Lng": "120.6486882"
        },
        {
            "magnitude": "32.64965543462902",
            "Lat": "24.1797638",
            "Lng": "120.648686"
        },
        {
            "magnitude": "32.64965543462902",
            "Lat": "24.1797638",
            "Lng": "120.648686"
        },
        {
            "magnitude": "66.76825593049439",
            "Lat": "24.179763",
            "Lng": "120.6486848"
        },
        {
            "magnitude": "66.76825593049439",
            "Lat": "24.179763",
            "Lng": "120.6486848"
        },
        {
            "magnitude": "45.902069670114",
            "Lat": "24.1797627",
            "Lng": "120.6486837"
        },
        {
            "magnitude": "45.902069670114",
            "Lat": "24.1797627",
            "Lng": "120.6486837"
        },
        {
            "magnitude": "37.12142238654117",
            "Lat": "24.1797604",
            "Lng": "120.6486546"
        },
        {
            "magnitude": "37.12142238654117",
            "Lat": "24.1797604",
            "Lng": "120.6486546"
        },
        {
            "magnitude": "37.33630940518894",
            "Lat": "24.1797633",
            "Lng": "120.6486433"
        },
        {
            "magnitude": "37.960505792204614",
            "Lat": "24.1797633",
            "Lng": "120.6486433"
        },
        {
            "magnitude": "26.419689627245813",
            "Lat": "24.1797541",
            "Lng": "120.6486398"
        },
        {
            "magnitude": "26.419689627245813",
            "Lat": "24.1797541",
            "Lng": "120.6486398"
        },
        {
            "magnitude": "39.92492955535426",
            "Lat": "24.1796329",
            "Lng": "120.6484469"
        },
        {
            "magnitude": "45.232731511594565",
            "Lat": "24.1796314",
            "Lng": "120.6484493"
        },
        {
            "magnitude": "45.232731511594565",
            "Lat": "24.1796314",
            "Lng": "120.6484493"
        },
        {
            "magnitude": "46.850827100489916",
            "Lat": "24.1796269",
            "Lng": "120.6484606"
        },
        {
            "magnitude": "46.850827100489916",
            "Lat": "24.1796269",
            "Lng": "120.6484606"
        },
        {
            "magnitude": "46.22769732530488",
            "Lat": "24.1796279",
            "Lng": "120.6484547"
        },
        {
            "magnitude": "45.58508528016593",
            "Lat": "24.1796296",
            "Lng": "120.6484527"
        },
        {
            "magnitude": "45.58508528016593",
            "Lat": "24.1796296",
            "Lng": "120.6484527"
        },
        {
            "magnitude": "48.010415536631214",
            "Lat": "24.1796307",
            "Lng": "120.648449"
        },
        {
            "magnitude": "48.85693400122443",
            "Lat": "24.1796316",
            "Lng": "120.6484569"
        },
        {
            "magnitude": "46.75467891024384",
            "Lat": "24.1796325",
            "Lng": "120.6484527"
        },
        {
            "magnitude": "46.75467891024384",
            "Lat": "24.1796325",
            "Lng": "120.6484527"
        },
        {
            "magnitude": "45.12205669071391",
            "Lat": "24.1796681",
            "Lng": "120.6484238"
        },
        {
            "magnitude": "45.12205669071391",
            "Lat": "24.1796681",
            "Lng": "120.6484238"
        },
        {
            "magnitude": "44.034077712607996",
            "Lat": "24.1796588",
            "Lng": "120.6483736"
        },
        {
            "magnitude": "44.034077712607996",
            "Lat": "24.1796588",
            "Lng": "120.6483736"
        },
        {
            "magnitude": "52.640288753007425",
            "Lat": "24.179694",
            "Lng": "120.6481767"
        },
        {
            "magnitude": "52.640288753007425",
            "Lat": "24.179694",
            "Lng": "120.6481767"
        },
        {
            "magnitude": "53.907327887774215",
            "Lat": "24.1797047",
            "Lng": "120.648169"
        },
        {
            "magnitude": "50.695167422546305",
            "Lat": "24.1796977",
            "Lng": "120.6477594"
        },
        {
            "magnitude": "50.695167422546305",
            "Lat": "24.1796977",
            "Lng": "120.6477594"
        },
        {
            "magnitude": "51.61395160225576",
            "Lat": "24.1796799",
            "Lng": "120.6477579"
        },
        {
            "magnitude": "51.61395160225576",
            "Lat": "24.1796799",
            "Lng": "120.6477579"
        },
        {
            "magnitude": "52.32590180780452",
            "Lat": "24.1796852",
            "Lng": "120.6477532"
        },
        {
            "magnitude": "52.01922721455981",
            "Lat": "24.1797002",
            "Lng": "120.6477414"
        },
        {
            "magnitude": "52.01922721455981",
            "Lat": "24.1797002",
            "Lng": "120.6477414"
        },
        {
            "magnitude": "53.71219600798314",
            "Lat": "24.1796978",
            "Lng": "120.6477204"
        },
        {
            "magnitude": "53.71219600798314",
            "Lat": "24.1796978",
            "Lng": "120.6477204"
        },
        {
            "magnitude": "54.08326913195984",
            "Lat": "24.1796714",
            "Lng": "120.6476963"
        },
        {
            "magnitude": "54.08326913195984",
            "Lat": "24.1796714",
            "Lng": "120.6476963"
        },
        {
            "magnitude": "50.60632371551998",
            "Lat": "24.1796877",
            "Lng": "120.6476751"
        },
        {
            "magnitude": "51.30302135352264",
            "Lat": "24.1797275",
            "Lng": "120.6476421"
        },
        {
            "magnitude": "51.36146415358503",
            "Lat": "24.1797441",
            "Lng": "120.6476245"
        },
        {
            "magnitude": "51.36146415358503",
            "Lat": "24.1797441",
            "Lng": "120.6476245"
        },
        {
            "magnitude": "51.67204273105525",
            "Lat": "24.1797489",
            "Lng": "120.6476054"
        },
        {
            "magnitude": "49.85980344927164",
            "Lat": "24.1797628",
            "Lng": "120.6475888"
        },
        {
            "magnitude": "49.85980344927164",
            "Lat": "24.1797628",
            "Lng": "120.6475888"
        },
        {
            "magnitude": "105.25207836427744",
            "Lat": "24.1806792",
            "Lng": "120.6464261"
        },
        {
            "magnitude": "35.014282800023196",
            "Lat": "24.1807199",
            "Lng": "120.6464102"
        },
        {
            "magnitude": "40.76763422127902",
            "Lat": "24.1807608",
            "Lng": "120.6463846"
        },
        {
            "magnitude": "43.18564576337837",
            "Lat": "24.1807785",
            "Lng": "120.6463799"
        },
        {
            "magnitude": "45.760244754590204",
            "Lat": "24.1807823",
            "Lng": "120.6463863"
        },
        {
            "magnitude": "50.73460357586329",
            "Lat": "24.180794",
            "Lng": "120.6463787"
        },
        {
            "magnitude": "50.73460357586329",
            "Lat": "24.180794",
            "Lng": "120.6463787"
        },
        {
            "magnitude": "50.60632371551998",
            "Lat": "24.1807979",
            "Lng": "120.6463777"
        },
        {
            "magnitude": "36.08323710533743",
            "Lat": "24.1808078",
            "Lng": "120.6463761"
        },
        {
            "magnitude": "36.08323710533743",
            "Lat": "24.1808078",
            "Lng": "120.6463761"
        },
        {
            "magnitude": "31.76476034853718",
            "Lat": "24.1808179",
            "Lng": "120.6463659"
        },
        {
            "magnitude": "31.76476034853718",
            "Lat": "24.1808179",
            "Lng": "120.6463659"
        },
        {
            "magnitude": "33.04542328371661",
            "Lat": "24.1808532",
            "Lng": "120.6463645"
        },
        {
            "magnitude": "30.95157508108432",
            "Lat": "24.1808748",
            "Lng": "120.6463474"
        },
        {
            "magnitude": "30.95157508108432",
            "Lat": "24.1808748",
            "Lng": "120.6463474"
        },
        {
            "magnitude": "28.035691537752374",
            "Lat": "24.1808896",
            "Lng": "120.6463333"
        },
        {
            "magnitude": "28.035691537752374",
            "Lat": "24.1808896",
            "Lng": "120.6463333"
        },
        {
            "magnitude": "33.54101966249684",
            "Lat": "24.1808993",
            "Lng": "120.6463322"
        },
        {
            "magnitude": "29.816103031751148",
            "Lat": "24.1809118",
            "Lng": "120.646329"
        },
        {
            "magnitude": "25.495097567963924",
            "Lat": "24.180922",
            "Lng": "120.6463277"
        },
        {
            "magnitude": "21.470910553583888",
            "Lat": "24.1809471",
            "Lng": "120.6463291"
        },
        {
            "magnitude": "21.470910553583888",
            "Lat": "24.1809471",
            "Lng": "120.6463291"
        },
        {
            "magnitude": "21.656407827707714",
            "Lat": "24.180954",
            "Lng": "120.6463228"
        },
        {
            "magnitude": "25.495097567963924",
            "Lat": "24.180962",
            "Lng": "120.6463258"
        },
        {
            "magnitude": "27.964262908219126",
            "Lat": "24.1809832",
            "Lng": "120.6462934"
        },
        {
            "magnitude": "34.0",
            "Lat": "24.1810102",
            "Lng": "120.6462898"
        },
        {
            "magnitude": "34.0",
            "Lat": "24.1810102",
            "Lng": "120.6462898"
        },
        {
            "magnitude": "29.13760456866693",
            "Lat": "24.1810217",
            "Lng": "120.6462871"
        },
        {
            "magnitude": "53.44155686354955",
            "Lat": "24.1809559",
            "Lng": "120.6465881"
        },
        {
            "magnitude": "53.44155686354955",
            "Lat": "24.1809559",
            "Lng": "120.6465881"
        },
        {
            "magnitude": "66.21933252457322",
            "Lat": "24.1809177",
            "Lng": "120.6465944"
        },
        {
            "magnitude": "66.21933252457322",
            "Lat": "24.1809177",
            "Lng": "120.6465944"
        },
        {
            "magnitude": "38.897300677553446",
            "Lat": "24.1808707",
            "Lng": "120.6466043"
        },
        {
            "magnitude": "38.897300677553446",
            "Lat": "24.1808707",
            "Lng": "120.6466043"
        },
        {
            "magnitude": "59.413803110051795",
            "Lat": "24.180795",
            "Lng": "120.6466073"
        },
        {
            "magnitude": "59.262129560116215",
            "Lat": "24.180795",
            "Lng": "120.6466073"
        },
        {
            "magnitude": "51.56549233741495",
            "Lat": "24.1807367",
            "Lng": "120.6466063"
        },
        {
            "magnitude": "51.56549233741495",
            "Lat": "24.1807367",
            "Lng": "120.6466063"
        },
        {
            "magnitude": "48.38388161361178",
            "Lat": "24.1806775",
            "Lng": "120.6465945"
        },
        {
            "magnitude": "48.38388161361178",
            "Lat": "24.1806775",
            "Lng": "120.6465945"
        },
        {
            "magnitude": "48.2078831727758",
            "Lat": "24.1806311",
            "Lng": "120.6465864"
        },
        {
            "magnitude": "48.2078831727758",
            "Lat": "24.1806311",
            "Lng": "120.6465864"
        },
        {
            "magnitude": "45.43126676640219",
            "Lat": "24.1805642",
            "Lng": "120.6465754"
        },
        {
            "magnitude": "45.43126676640219",
            "Lat": "24.1805642",
            "Lng": "120.6465754"
        },
        {
            "magnitude": "47.138094997570704",
            "Lat": "24.1805117",
            "Lng": "120.6465696"
        },
        {
            "magnitude": "47.138094997570704",
            "Lat": "24.1805117",
            "Lng": "120.6465696"
        },
        {
            "magnitude": "43.70354676682432",
            "Lat": "24.1799664",
            "Lng": "120.6467622"
        },
        {
            "magnitude": "43.70354676682432",
            "Lat": "24.1799664",
            "Lng": "120.6467622"
        },
        {
            "magnitude": "43.94314508543966",
            "Lat": "24.1799686",
            "Lng": "120.6467666"
        },
        {
            "magnitude": "43.94314508543966",
            "Lat": "24.1799686",
            "Lng": "120.6467666"
        },
        {
            "magnitude": "34.77067730142742",
            "Lat": "24.1799762",
            "Lng": "120.6467795"
        },
        {
            "magnitude": "34.77067730142742",
            "Lat": "24.1799762",
            "Lng": "120.6467795"
        },
        {
            "magnitude": "42.485291572496",
            "Lat": "24.1799789",
            "Lng": "120.6467878"
        },
        {
            "magnitude": "42.485291572496",
            "Lat": "24.1799789",
            "Lng": "120.6467878"
        },
        {
            "magnitude": "38.600518131237564",
            "Lat": "24.1800027",
            "Lng": "120.6470791"
        },
        {
            "magnitude": "38.600518131237564",
            "Lat": "24.1800027",
            "Lng": "120.6470791"
        },
        {
            "magnitude": "41.15823125451335",
            "Lat": "24.1800049",
            "Lng": "120.6470708"
        },
        {
            "magnitude": "41.15823125451335",
            "Lat": "24.1800049",
            "Lng": "120.6470708"
        },
        {
            "magnitude": "38.49675310984031",
            "Lat": "24.1800087",
            "Lng": "120.6470619"
        },
        {
            "magnitude": "38.49675310984031",
            "Lat": "24.1800087",
            "Lng": "120.6470619"
        },
        {
            "magnitude": "47.07440918375928",
            "Lat": "24.1800064",
            "Lng": "120.6470955"
        },
        {
            "magnitude": "46.33573135281238",
            "Lat": "24.1800064",
            "Lng": "120.6470955"
        },
        {
            "magnitude": "47.60252094164762",
            "Lat": "24.1800076",
            "Lng": "120.6471246"
        },
        {
            "magnitude": "47.60252094164762",
            "Lat": "24.1800076",
            "Lng": "120.6471246"
        },
        {
            "magnitude": "46.57252408878007",
            "Lat": "24.1800102",
            "Lng": "120.6471732"
        },
        {
            "magnitude": "46.57252408878007",
            "Lat": "24.1800102",
            "Lng": "120.6471732"
        },
        {
            "magnitude": "46.24932431938871",
            "Lat": "24.1800067",
            "Lng": "120.6472057"
        },
        {
            "magnitude": "46.24932431938871",
            "Lat": "24.1800067",
            "Lng": "120.6472057"
        },
        {
            "magnitude": "46.486557196677836",
            "Lat": "24.180006",
            "Lng": "120.6472363"
        },
        {
            "magnitude": "46.486557196677836",
            "Lat": "24.180006",
            "Lng": "120.6472363"
        },
        {
            "magnitude": "45.8475735453906",
            "Lat": "24.1800273",
            "Lng": "120.6472776"
        },
        {
            "magnitude": "45.8475735453906",
            "Lat": "24.1800273",
            "Lng": "120.6472776"
        },
        {
            "magnitude": "44.87761134463375",
            "Lat": "24.1800784",
            "Lng": "120.647302"
        },
        {
            "magnitude": "44.87761134463375",
            "Lat": "24.1800784",
            "Lng": "120.647302"
        },
        {
            "magnitude": "44.955533585978046",
            "Lat": "24.1801108",
            "Lng": "120.6473224"
        },
        {
            "magnitude": "45.58508528016593",
            "Lat": "24.1801108",
            "Lng": "120.6473224"
        },
        {
            "magnitude": "45.45327270945405",
            "Lat": "24.1801218",
            "Lng": "120.647325"
        },
        {
            "magnitude": "43.289721643826724",
            "Lat": "24.1799354",
            "Lng": "120.6478133"
        },
        {
            "magnitude": "44.69899327725402",
            "Lat": "24.1799365",
            "Lng": "120.647818"
        },
        {
            "magnitude": "44.73253849269008",
            "Lat": "24.1799378",
            "Lng": "120.6478218"
        },
        {
            "magnitude": "46.400431032480725",
            "Lat": "24.179942",
            "Lng": "120.6478351"
        },
        {
            "magnitude": "46.400431032480725",
            "Lat": "24.1799449",
            "Lng": "120.6478461"
        },
        {
            "magnitude": "43.382023926967726",
            "Lat": "24.1799506",
            "Lng": "120.6478535"
        },
        {
            "magnitude": "43.382023926967726",
            "Lat": "24.1799506",
            "Lng": "120.6478535"
        },
        {
            "magnitude": "40.36087214122113",
            "Lat": "24.1799577",
            "Lng": "120.6478632"
        },
        {
            "magnitude": "43.87482193696061",
            "Lat": "24.1799586",
            "Lng": "120.6478714"
        },
        {
            "magnitude": "44.02272140611028",
            "Lat": "24.1799498",
            "Lng": "120.647881"
        },
        {
            "magnitude": "41.47288270665544",
            "Lat": "24.1799462",
            "Lng": "120.647891"
        },
        {
            "magnitude": "41.701318923986086",
            "Lat": "24.1799472",
            "Lng": "120.6478959"
        },
        {
            "magnitude": "41.701318923986086",
            "Lat": "24.1799472",
            "Lng": "120.6478959"
        },
        {
            "magnitude": "43.61192497471305",
            "Lat": "24.1799483",
            "Lng": "120.6479006"
        },
        {
            "magnitude": "43.61192497471305",
            "Lat": "24.1799483",
            "Lng": "120.6479006"
        },
        {
            "magnitude": "42.555845661906424",
            "Lat": "24.1799572",
            "Lng": "120.6479172"
        },
        {
            "magnitude": "43.46262762420146",
            "Lat": "24.1795951",
            "Lng": "120.6483465"
        },
        {
            "magnitude": "44.384682042344295",
            "Lat": "24.179621",
            "Lng": "120.6483764"
        },
        {
            "magnitude": "44.384682042344295",
            "Lat": "24.179621",
            "Lng": "120.6483764"
        },
        {
            "magnitude": "44.05678154382138",
            "Lat": "24.1795927",
            "Lng": "120.6483691"
        },
        {
            "magnitude": "45.617978911828175",
            "Lat": "24.1795771",
            "Lng": "120.6483635"
        },
        {
            "magnitude": "46.54030511288038",
            "Lat": "24.1795325",
            "Lng": "120.6483353"
        },
        {
            "magnitude": "44.77722635447622",
            "Lat": "24.1794641",
            "Lng": "120.6483234"
        },
        {
            "magnitude": "48.80573736764972",
            "Lat": "24.1794446",
            "Lng": "120.6483104"
        },
        {
            "magnitude": "57.105166141076936",
            "Lat": "24.1790949",
            "Lng": "120.6481924"
        },
        {
            "magnitude": "57.105166141076936",
            "Lat": "24.1790949",
            "Lng": "120.6481924"
        },
        {
            "magnitude": "60.241181927316134",
            "Lat": "24.179108",
            "Lng": "120.6481985"
        },
        {
            "magnitude": "60.241181927316134",
            "Lat": "24.179108",
            "Lng": "120.6481985"
        },
        {
            "magnitude": "54.89080068645383",
            "Lat": "24.179109",
            "Lng": "120.6482013"
        },
        {
            "magnitude": "54.89080068645383",
            "Lat": "24.179109",
            "Lng": "120.6482013"
        },
        {
            "magnitude": "50.60632371551998",
            "Lat": "24.1791181",
            "Lng": "120.6482095"
        },
        {
            "magnitude": "50.60632371551998",
            "Lat": "24.1791181",
            "Lng": "120.6482095"
        },
        {
            "magnitude": "55.308227236099334",
            "Lat": "24.179123",
            "Lng": "120.6482137"
        },
        {
            "magnitude": "55.308227236099334",
            "Lat": "24.179123",
            "Lng": "120.6482137"
        },
        {
            "magnitude": "43.05810028322197",
            "Lat": "24.1792956",
            "Lng": "120.6485049"
        },
        {
            "magnitude": "43.05810028322197",
            "Lat": "24.1792956",
            "Lng": "120.6485049"
        },
        {
            "magnitude": "37.067505985701274",
            "Lat": "24.179104",
            "Lng": "120.6482015"
        },
        {
            "magnitude": "37.067505985701274",
            "Lat": "24.179104",
            "Lng": "120.6482015"
        },
        {
            "magnitude": "39.21734310225516",
            "Lat": "24.1792989",
            "Lng": "120.6482151"
        },
        {
            "magnitude": "36.90528417449187",
            "Lat": "24.1792637",
            "Lng": "120.6482471"
        },
        {
            "magnitude": "38.61346915261564",
            "Lat": "24.1792418",
            "Lng": "120.6482352"
        },
        {
            "magnitude": "37.0",
            "Lat": "24.179314",
            "Lng": "120.6483167"
        },
        {
            "magnitude": "32.526911934581186",
            "Lat": "24.179426",
            "Lng": "120.6483047"
        },
        {
            "magnitude": "40.0374824383352",
            "Lat": "24.1795236",
            "Lng": "120.6483155"
        },
        {
            "magnitude": "37.429934544425805",
            "Lat": "24.1795535",
            "Lng": "120.6483256"
        },
        {
            "magnitude": "38.52272056851645",
            "Lat": "24.1795775",
            "Lng": "120.6483174"
        },
        {
            "magnitude": "38.52272056851645",
            "Lat": "24.1795775",
            "Lng": "120.6483174"
        },
        {
            "magnitude": "36.40054944640259",
            "Lat": "24.1795837",
            "Lng": "120.648334"
        },
        {
            "magnitude": "37.69615364994153",
            "Lat": "24.1796108",
            "Lng": "120.6483421"
        },
        {
            "magnitude": "33.481338085566414",
            "Lat": "24.1796262",
            "Lng": "120.6483438"
        },
        {
            "magnitude": "29.34280150224242",
            "Lat": "24.1795752",
            "Lng": "120.6486131"
        },
        {
            "magnitude": "29.0",
            "Lat": "24.1795637",
            "Lng": "120.6486073"
        },
        {
            "magnitude": "25.495097567963924",
            "Lat": "24.1795692",
            "Lng": "120.6486118"
        },
        {
            "magnitude": "27.202941017470888",
            "Lat": "24.1795704",
            "Lng": "120.6486203"
        },
        {
            "magnitude": "30.805843601498726",
            "Lat": "24.1795783",
            "Lng": "120.6486273"
        },
        {
            "magnitude": "25.41653005427767",
            "Lat": "24.1795939",
            "Lng": "120.6486197"
        },
        {
            "magnitude": "33.015148038438355",
            "Lat": "24.1796061",
            "Lng": "120.6486119"
        },
        {
            "magnitude": "36.41428291206625",
            "Lat": "24.1796135",
            "Lng": "120.6486078"
        },
        {
            "magnitude": "36.41428291206625",
            "Lat": "24.1796135",
            "Lng": "120.6486078"
        },
        {
            "magnitude": "35.749125863438955",
            "Lat": "24.1796165",
            "Lng": "120.6486071"
        },
        {
            "magnitude": "37.986839826445156",
            "Lat": "24.179623",
            "Lng": "120.6486029"
        },
        {
            "magnitude": "34.336569426778794",
            "Lat": "24.1796297",
            "Lng": "120.648598"
        },
        {
            "magnitude": "34.336569426778794",
            "Lat": "24.1796297",
            "Lng": "120.648598"
        },
        {
            "magnitude": "32.95451410656816",
            "Lat": "24.1796359",
            "Lng": "120.6485718"
        },
        {
            "magnitude": "37.960505792204614",
            "Lat": "24.1796416",
            "Lng": "120.6485646"
        },
        {
            "magnitude": "38.7556447501522",
            "Lat": "24.1796472",
            "Lng": "120.6485579"
        },
        {
            "magnitude": "40.50925820105819",
            "Lat": "24.1796556",
            "Lng": "120.6485562"
        },
        {
            "magnitude": "40.50925820105819",
            "Lat": "24.1796556",
            "Lng": "120.6485562"
        },
        {
            "magnitude": "40.50925820105819",
            "Lat": "24.1796556",
            "Lng": "120.6485562"
        },
        {
            "magnitude": "40.50925820105819",
            "Lat": "24.1796556",
            "Lng": "120.6485562"
        },
        {
            "magnitude": "40.50925820105819",
            "Lat": "24.1796556",
            "Lng": "120.6485562"
        },
        {
            "magnitude": "40.50925820105819",
            "Lat": "24.1796556",
            "Lng": "120.6485562"
        },
        {
            "magnitude": "40.50925820105819",
            "Lat": "24.1796556",
            "Lng": "120.6485562"
        },
        {
            "magnitude": "40.50925820105819",
            "Lat": "24.1796556",
            "Lng": "120.6485562"
        },
        {
            "magnitude": "40.50925820105819",
            "Lat": "24.1796556",
            "Lng": "120.6485562"
        },
        {
            "magnitude": "40.50925820105819",
            "Lat": "24.1796556",
            "Lng": "120.6485562"
        },
        {
            "magnitude": "40.50925820105819",
            "Lat": "24.1796556",
            "Lng": "120.6485562"
        },
        {
            "magnitude": "40.50925820105819",
            "Lat": "24.1796556",
            "Lng": "120.6485562"
        },
        {
            "magnitude": "40.50925820105819",
            "Lat": "24.1796556",
            "Lng": "120.6485562"
        },
        {
            "magnitude": "40.50925820105819",
            "Lat": "24.1796556",
            "Lng": "120.6485562"
        },
        {
            "magnitude": "40.50925820105819",
            "Lat": "24.1796556",
            "Lng": "120.6485562"
        },
        {
            "magnitude": "40.50925820105819",
            "Lat": "24.1796556",
            "Lng": "120.6485562"
        },
        {
            "magnitude": "43.749285708454714",
            "Lat": "24.179754",
            "Lng": "120.6486869"
        },
        {
            "magnitude": "43.9203825119955",
            "Lat": "24.1797539",
            "Lng": "120.6486865"
        },
        {
            "magnitude": "43.9203825119955",
            "Lat": "24.1797539",
            "Lng": "120.6486865"
        },
        {
            "magnitude": "44.8998886412873",
            "Lat": "24.1797537",
            "Lng": "120.6486862"
        },
        {
            "magnitude": "44.8998886412873",
            "Lat": "24.1797537",
            "Lng": "120.6486862"
        },
        {
            "magnitude": "44.8998886412873",
            "Lat": "24.1797538",
            "Lng": "120.6486863"
        },
        {
            "magnitude": "44.8998886412873",
            "Lat": "24.1797538",
            "Lng": "120.6486863"
        },
        {
            "magnitude": "44.8998886412873",
            "Lat": "24.1797539",
            "Lng": "120.6486864"
        },
        {
            "magnitude": "44.73253849269008",
            "Lat": "24.1797539",
            "Lng": "120.6486864"
        },
        {
            "magnitude": "44.73253849269008",
            "Lat": "24.1797541",
            "Lng": "120.6486866"
        },
        {
            "magnitude": "44.73253849269008",
            "Lat": "24.1797541",
            "Lng": "120.6486866"
        },
        {
            "magnitude": "43.749285708454714",
            "Lat": "24.1797563",
            "Lng": "120.6486866"
        },
        {
            "magnitude": "43.749285708454714",
            "Lat": "24.1797563",
            "Lng": "120.6486866"
        },
        {
            "magnitude": "36.4417343165772",
            "Lat": "24.1797557",
            "Lng": "120.6486865"
        },
        {
            "magnitude": "36.4417343165772",
            "Lat": "24.1797557",
            "Lng": "120.6486865"
        },
        {
            "magnitude": "10.862780491200215",
            "Lat": "24.1797553",
            "Lng": "120.6486863"
        },
        {
            "magnitude": "10.862780491200215",
            "Lat": "24.1797553",
            "Lng": "120.6486863"
        }
    ]
}